datapizza/clients/openai/__init__.py
datapizza/clients/openai/memory_adapter.py
datapizza/clients/openai/openai_client.py
datapizza_ai_clients_openai-0.0.9.dist-info/METADATA
datapizza_ai_clients_openai-0.0.9.dist-info/WHEEL
datapizza_ai_clients_openai-0.0.9.dist-info/RECORD
