Metadata-Version: 2.4
Name: datapizza-ai-clients-openai
Version: 0.0.9
Summary: OpenAI client for the datapizza-ai framework
License: MIT
Classifier: License :: OSI Approved :: MIT License
Classifier: Operating System :: OS Independent
Classifier: Programming Language :: Python :: 3
Requires-Python: <4,>=3.10.0
Requires-Dist: datapizza-ai-core<0.1.0,>=0.0.7
Requires-Dist: openai<3.0.0,>=2
